{
  "file": "BDC_G11.prg",
  "status": "ok",
  "jobs": [
    {
      "name": "INFO",
      "status": "ok",
      "instructions": 36,
      "errors": []
    },
    {
      "name": "INITIALISIERUNG",
      "status": "ok",
      "instructions": 42,
      "errors": []
    },
    {
      "name": "IDENT",
      "status": "ok",
      "instructions": 181,
      "errors": []
    },
    {
      "name": "FS_LESEN",
      "status": "ok",
      "instructions": 301,
      "errors": []
    },
    {
      "name": "FS_LESEN_DETAIL",
      "status": "ok",
      "instructions": 156,
      "errors": []
    },
    {
      "name": "FS_LOESCHEN",
      "status": "ok",
      "instructions": 254,
      "errors": []
    },
    {
      "name": "PRUEFSTEMPEL_LESEN",
      "status": "ok",
      "instructions": 181,
      "errors": []
    },
    {
      "name": "PRUEFSTEMPEL_SCHREIBEN",
      "status": "ok",
      "instructions": 68,
      "errors": []
    },
    {
      "name": "SVK_LESEN",
      "status": "ok",
      "instructions": 112,
      "errors": []
    },
    {
      "name": "STATUS_LESEN",
      "status": "ok",
      "instructions": 190,
      "errors": []
    },
    {
      "name": "STEUERN",
      "status": "ok",
      "instructions": 190,
      "errors": []
    },
    {
      "name": "SERIENNUMMER_LESEN",
      "status": "ok",
      "instructions": 181,
      "errors": []
    },
    {
      "name": "STEUERN_IO",
      "status": "ok",
      "instructions": 190,
      "errors": []
    },
    {
      "name": "STEUERN_ROUTINE",
      "status": "ok",
      "instructions": 190,
      "errors": []
    },
    {
      "name": "FS_SPERREN",
      "status": "ok",
      "instructions": 79,
      "errors": []
    },
    {
      "name": "IS_LESEN",
      "status": "ok",
      "instructions": 190,
      "errors": []
    },
    {
      "name": "IS_LESEN_DETAIL",
      "status": "ok",
      "instructions": 171,
      "errors": []
    },
    {
      "name": "IS_LOESCHEN",
      "status": "ok",
      "instructions": 181,
      "errors": []
    },
    {
      "name": "HERSTELLINFO_LESEN",
      "status": "ok",
      "instructions": 666,
      "errors": []
    },
    {
      "name": "DIAGNOSE_AUFRECHT",
      "status": "ok",
      "instructions": 71,
      "errors": []
    },
    {
      "name": "DIAGNOSE_MODE",
      "status": "ok",
      "instructions": 85,
      "errors": []
    },
    {
      "name": "SLEEP_MODE",
      "status": "ok",
      "instructions": 181,
      "errors": []
    },
    {
      "name": "ENERGIESPARMODE",
      "status": "ok",
      "instructions": 64,
      "errors": []
    },
    {
      "name": "STATUS_ENERGIESPARMODE",
      "status": "ok",
      "instructions": 181,
      "errors": []
    },
    {
      "name": "STATUS_BETRIEBSMODE",
      "status": "ok",
      "instructions": 181,
      "errors": []
    },
    {
      "name": "STEUERN_BETRIEBSMODE",
      "status": "ok",
      "instructions": 62,
      "errors": []
    },
    {
      "name": "SENSOREN_ANZAHL_LESEN",
      "status": "ok",
      "instructions": 181,
      "errors": []
    },
    {
      "name": "SENSOREN_IDENT_LESEN",
      "status": "ok",
      "instructions": 151,
      "errors": []
    },
    {
      "name": "STEUERGERAETE_RESET",
      "status": "ok",
      "instructions": 181,
      "errors": []
    },
    {
      "name": "STATUS_ROE_REPORT",
      "status": "ok",
      "instructions": 468,
      "errors": []
    },
    {
      "name": "STEUERN_ROE_PERSISTENT_STOP",
      "status": "ok",
      "instructions": 222,
      "errors": []
    },
    {
      "name": "STEUERN_ROE_PERSISTENT_START",
      "status": "ok",
      "instructions": 222,
      "errors": []
    },
    {
      "name": "CALID_CVN_LESEN",
      "status": "ok",
      "instructions": 207,
      "errors": []
    },
    {
      "name": "CPS_LESEN",
      "status": "ok",
      "instructions": 193,
      "errors": []
    },
    {
      "name": "DIAG_SESSION_LESEN",
      "status": "ok",
      "instructions": 181,
      "errors": []
    },
    {
      "name": "FLASH_TP_LESEN",
      "status": "ok",
      "instructions": 181,
      "errors": []
    },
    {
      "name": "STATUS_ANF_ZUSTAND_FZG",
      "status": "ok",
      "instructions": 181,
      "errors": []
    },
    {
      "name": "STATUS_BATTERIEVORSCHAEDIGUNGSHISTORIE",
      "status": "ok",
      "instructions": 181,
      "errors": []
    },
    {
      "name": "STATUS_CAS_INIT_LOC_DATE",
      "status": "ok",
      "instructions": 181,
      "errors": []
    },
    {
      "name": "STATUS_CA_BEDIENSTELLEN",
      "status": "ok",
      "instructions": 181,
      "errors": []
    },
    {
      "name": "STATUS_ECUMA_AWAKE",
      "status": "ok",
      "instructions": 181,
      "errors": []
    },
    {
      "name": "STATUS_ECUMA_HISTORIE",
      "status": "ok",
      "instructions": 181,
      "errors": []
    },
    {
      "name": "STATUS_ELSV",
      "status": "ok",
      "instructions": 181,
      "errors": []
    },
    {
      "name": "STATUS_ELSV_STATISTIK",
      "status": "ok",
      "instructions": 185,
      "errors": []
    },
    {
      "name": "STATUS_EM_FE_MODE",
      "status": "ok",
      "instructions": 181,
      "errors": []
    },
    {
      "name": "STATUS_EM_SPIELSCHUTZ",
      "status": "ok",
      "instructions": 181,
      "errors": []
    },
    {
      "name": "STATUS_FAHRGESTELLNUMMER",
      "status": "ok",
      "instructions": 181,
      "errors": []
    },
    {
      "name": "STATUS_FAHRPROFIL",
      "status": "ok",
      "instructions": 185,
      "errors": []
    },
    {
      "name": "STATUS_FBD_EMPFAENGER",
      "status": "ok",
      "instructions": 181,
      "errors": []
    },
    {
      "name": "STATUS_FBD_FEHLER",
      "status": "ok",
      "instructions": 181,
      "errors": []
    },
    {
      "name": "STATUS_FBD_TELEGRAMM",
      "status": "ok",
      "instructions": 228,
      "errors": []
    },
    {
      "name": "STATUS_FH_BEWERTUNG_KENNLINIEN",
      "status": "ok",
      "instructions": 171,
      "errors": []
    },
    {
      "name": "STATUS_FH_DENORMIERUNGS_LOGGER_LESEN",
      "status": "ok",
      "instructions": 401,
      "errors": []
    },
    {
      "name": "STATUS_FH_MOTORSTOP_LOGGER_LESEN",
      "status": "ok",
      "instructions": 253,
      "errors": []
    },
    {
      "name": "STATUS_FH_REVERSIER_LOGGER_LESEN",
      "status": "ok",
      "instructions": 401,
      "errors": []
    },
    {
      "name": "STATUS_FH_SCHLIESSZEIT_HINTEN",
      "status": "ok",
      "instructions": 185,
      "errors": []
    },
    {
      "name": "STATUS_FH_SCHLIESSZEIT_VORNE",
      "status": "ok",
      "instructions": 185,
      "errors": []
    },
    {
      "name": "STATUS_FH_THERMOMONITOR_AKTIV",
      "status": "ok",
      "instructions": 305,
      "errors": []
    },
    {
      "name": "STATUS_HW_OPTIONEN_VARIANTE",
      "status": "ok",
      "instructions": 181,
      "errors": []
    },
    {
      "name": "STATUS_IM",
      "status": "ok",
      "instructions": 181,
      "errors": []
    },
    {
      "name": "STATUS_IM_ADEV_DATA",
      "status": "ok",
      "instructions": 95,
      "errors": []
    },
    {
      "name": "STATUS_IM_ANLIEFERZUSTAND",
      "status": "ok",
      "instructions": 181,
      "errors": []
    },
    {
      "name": "STATUS_IM_CURRENT_TRSP",
      "status": "ok",
      "instructions": 181,
      "errors": []
    },
    {
      "name": "STATUS_IM_FREQ_CONF",
      "status": "ok",
      "instructions": 181,
      "errors": []
    },
    {
      "name": "STATUS_IM_WUP",
      "status": "ok",
      "instructions": 181,
      "errors": []
    },
    {
      "name": "STATUS_INNENLICHT_AUTOADRESSIERUNGSFEHLER",
      "status": "ok",
      "instructions": 181,
      "errors": []
    },
    {
      "name": "STATUS_JBR_STATISTIK",
      "status": "ok",
      "instructions": 185,
      "errors": []
    },
    {
      "name": "STATUS_KEYINFO_DATEN",
      "status": "ok",
      "instructions": 181,
      "errors": []
    },
    {
      "name": "STATUS_KILOMETERSTAND",
      "status": "ok",
      "instructions": 185,
      "errors": []
    },
    {
      "name": "STATUS_KL15_KURZSCHLUSS_WIEDERAKTIVIERUNG_COUNTER",
      "status": "ok",
      "instructions": 197,
      "errors": []
    },
    {
      "name": "STATUS_KLEMMENSPANNUNG_LESEN",
      "status": "ok",
      "instructions": 181,
      "errors": []
    },
    {
      "name": "STATUS_KLEMMEN_HISTORIE",
      "status": "ok",
      "instructions": 181,
      "errors": []
    },
    {
      "name": "STATUS_KURZSCHLUSSABSCHALTUNG",
      "status": "ok",
      "instructions": 197,
      "errors": []
    },
    {
      "name": "STATUS_KURZSCHLUSSCOUNTER_ABS",
      "status": "ok",
      "instructions": 197,
      "errors": []
    },
    {
      "name": "STATUS_LEUCHTENAUSGANG_DIGITAL",
      "status": "ok",
      "instructions": 197,
      "errors": []
    },
    {
      "name": "STATUS_LEUCHTEN_BETRIEBSDAUER",
      "status": "ok",
      "instructions": 197,
      "errors": []
    },
    {
      "name": "STATUS_LIMP_HOME_ANALYSE",
      "status": "ok",
      "instructions": 185,
      "errors": []
    },
    {
      "name": "STATUS_NFC_READER_STATUS",
      "status": "ok",
      "instructions": 87,
      "errors": []
    },
    {
      "name": "STATUS_RCS_BATTERIESTATUS",
      "status": "ok",
      "instructions": 185,
      "errors": []
    },
    {
      "name": "STATUS_RDU_RDL_INFO",
      "status": "ok",
      "instructions": 201,
      "errors": []
    },
    {
      "name": "STATUS_SCHLUESSELSUCHEN_HISTORIE",
      "status": "ok",
      "instructions": 181,
      "errors": []
    },
    {
      "name": "STATUS_SENSE_LESEN",
      "status": "ok",
      "instructions": 24,
      "errors": []
    },
    {
      "name": "STATUS_SERVICESCHLUESSELDATEN_AKTUALISIERUNGSSTATUSBYTES",
      "status": "ok",
      "instructions": 101,
      "errors": []
    },
    {
      "name": "STATUS_STANDNUTZUNG_HISTORIE_10",
      "status": "ok",
      "instructions": 181,
      "errors": []
    },
    {
      "name": "STATUS_STANDNUTZUNG_HISTORIE_40",
      "status": "ok",
      "instructions": 181,
      "errors": []
    },
    {
      "name": "STATUS_SW_COMPONENTS",
      "status": "ok",
      "instructions": 181,
      "errors": []
    },
    {
      "name": "STATUS_THS_FFB_DATEN",
      "status": "ok",
      "instructions": 133,
      "errors": []
    },
    {
      "name": "STATUS_WCA_STATUS",
      "status": "ok",
      "instructions": 181,
      "errors": []
    },
    {
      "name": "STATUS_ZV_AKTUELL",
      "status": "ok",
      "instructions": 185,
      "errors": []
    },
    {
      "name": "STATUS_ZV_BEDIENSTELLEN",
      "status": "ok",
      "instructions": 181,
      "errors": []
    },
    {
      "name": "STATUS_ZV_HISTORIE",
      "status": "ok",
      "instructions": 181,
      "errors": []
    },
    {
      "name": "STATUS_ZV_KLAPPEN",
      "status": "ok",
      "instructions": 181,
      "errors": []
    },
    {
      "name": "STATUS_ZV_KONTAKTE",
      "status": "ok",
      "instructions": 181,
      "errors": []
    },
    {
      "name": "STEUERGERAETE_RESET_FAST",
      "status": "ok",
      "instructions": 181,
      "errors": []
    },
    {
      "name": "STEUERN_CAS_INIT_LOC_DATE",
      "status": "ok",
      "instructions": 27,
      "errors": []
    },
    {
      "name": "STEUERN_ECUMA_HISTORIE",
      "status": "ok",
      "instructions": 181,
      "errors": []
    },
    {
      "name": "STEUERN_ELSV_DENORMIEREN",
      "status": "ok",
      "instructions": 181,
      "errors": []
    },
    {
      "name": "STEUERN_ELSV_NORMIERUNG",
      "status": "ok",
      "instructions": 28,
      "errors": []
    },
    {
      "name": "STEUERN_ELSV_RESET_ZAEHLER",
      "status": "ok",
      "instructions": 48,
      "errors": []
    },
    {
      "name": "STEUERN_EM_FE_MODE",
      "status": "ok",
      "instructions": 211,
      "errors": []
    },
    {
      "name": "STEUERN_FAHRGESTELLNUMMER",
      "status": "ok",
      "instructions": 37,
      "errors": []
    },
    {
      "name": "STEUERN_FENSTERHEBER",
      "status": "ok",
      "instructions": 90,
      "errors": []
    },
    {
      "name": "STEUERN_FENSTERHEBER_DENORMIEREN",
      "status": "ok",
      "instructions": 24,
      "errors": []
    },
    {
      "name": "STEUERN_FENSTERHEBER_KENNLINIE_LOESCHEN",
      "status": "ok",
      "instructions": 24,
      "errors": []
    },
    {
      "name": "STEUERN_FH_DENORMIERUNGS_LOGGER_LOESCHEN",
      "status": "ok",
      "instructions": 24,
      "errors": []
    },
    {
      "name": "STEUERN_FH_MOTORSTOP_LOGGER_LOESCHEN",
      "status": "ok",
      "instructions": 24,
      "errors": []
    },
    {
      "name": "STEUERN_FH_REVERSIER_LOGGER_LOESCHEN",
      "status": "ok",
      "instructions": 24,
      "errors": []
    },
    {
      "name": "STEUERN_FH_THERMOMONITOR_AKTIV",
      "status": "ok",
      "instructions": 24,
      "errors": []
    },
    {
      "name": "STEUERN_IM_ADEV_DATA",
      "status": "ok",
      "instructions": 117,
      "errors": []
    },
    {
      "name": "STEUERN_IM_ANLIEFERZUSTAND_START",
      "status": "ok",
      "instructions": 100,
      "errors": []
    },
    {
      "name": "STEUERN_IM_DATA",
      "status": "ok",
      "instructions": 81,
      "errors": []
    },
    {
      "name": "STEUERN_IM_FREQ_CONF",
      "status": "ok",
      "instructions": 149,
      "errors": []
    },
    {
      "name": "STEUERN_IM_OP",
      "status": "ok",
      "instructions": 138,
      "errors": []
    },
    {
      "name": "STEUERN_IM_TRSP_INIT",
      "status": "ok",
      "instructions": 117,
      "errors": []
    },
    {
      "name": "STEUERN_IM_WUP",
      "status": "ok",
      "instructions": 420,
      "errors": []
    },
    {
      "name": "STEUERN_INIT_KURZSCHLUSSCOUNTER_ABS",
      "status": "ok",
      "instructions": 185,
      "errors": []
    },
    {
      "name": "STEUERN_JBR_STATISTIK_RESET",
      "status": "ok",
      "instructions": 181,
      "errors": []
    },
    {
      "name": "STEUERN_KEYINFO_DATEN_UPDATE",
      "status": "ok",
      "instructions": 140,
      "errors": []
    },
    {
      "name": "STEUERN_KL30F",
      "status": "ok",
      "instructions": 36,
      "errors": []
    },
    {
      "name": "STEUERN_KLEMMEN",
      "status": "ok",
      "instructions": 36,
      "errors": []
    },
    {
      "name": "STEUERN_LEUCHTENAUSGANG_DIGITAL",
      "status": "ok",
      "instructions": 32,
      "errors": []
    },
    {
      "name": "STEUERN_LIN_QUERY",
      "status": "ok",
      "instructions": 109,
      "errors": []
    },
    {
      "name": "STEUERN_PIA_NR",
      "status": "ok",
      "instructions": 128,
      "errors": []
    },
    {
      "name": "STEUERN_RCS_BATTERIESTATUS",
      "status": "ok",
      "instructions": 32,
      "errors": []
    },
    {
      "name": "STEUERN_RESET_BETRIEBSDAUER",
      "status": "ok",
      "instructions": 32,
      "errors": []
    },
    {
      "name": "STEUERN_RESET_LICHT_UEBERSPANNUNGSCOUNTER",
      "status": "ok",
      "instructions": 185,
      "errors": []
    },
    {
      "name": "STEUERN_SCHLUESSEL_SPERRE",
      "status": "ok",
      "instructions": 27,
      "errors": []
    },
    {
      "name": "STEUERN_THS_FFB_INIT",
      "status": "ok",
      "instructions": 165,
      "errors": []
    },
    {
      "name": "STEUERN_ZUSTAND_FAHRZEUG",
      "status": "ok",
      "instructions": 36,
      "errors": []
    },
    {
      "name": "_STATUS_FUSI_SAFEMECH_INTERVENTION",
      "status": "ok",
      "instructions": 181,
      "errors": []
    },
    {
      "name": "_STATUS_JTAG_ENCRYPTED",
      "status": "ok",
      "instructions": 181,
      "errors": []
    },
    {
      "name": "_STEUERN_JTAG_ENCRYPTED",
      "status": "ok",
      "instructions": 36,
      "errors": []
    },
    {
      "name": "_STEUERN_JTAG_RANDOM",
      "status": "ok",
      "instructions": 440,
      "errors": []
    },
    {
      "name": "_STEUERN_KURZSCHLUSSCOUNTER_ABS",
      "status": "ok",
      "instructions": 32,
      "errors": []
    }
  ]
}