{
  "file": "dsc_l30.prg",
  "status": "ok",
  "jobs": [
    {
      "name": "INFO",
      "status": "ok",
      "instructions": 36,
      "errors": []
    },
    {
      "name": "INITIALISIERUNG",
      "status": "ok",
      "instructions": 42,
      "errors": []
    },
    {
      "name": "IDENT",
      "status": "ok",
      "instructions": 102,
      "errors": []
    },
    {
      "name": "LOGIN",
      "status": "ok",
      "instructions": 102,
      "errors": []
    },
    {
      "name": "FS_LESEN",
      "status": "ok",
      "instructions": 152,
      "errors": []
    },
    {
      "name": "FS_LESEN_SAR",
      "status": "ok",
      "instructions": 152,
      "errors": []
    },
    {
      "name": "FS_LOESCHEN",
      "status": "ok",
      "instructions": 125,
      "errors": []
    },
    {
      "name": "COD_LESEN",
      "status": "ok",
      "instructions": 369,
      "errors": []
    },
    {
      "name": "COD_SCHREIBEN",
      "status": "ok",
      "instructions": 355,
      "errors": []
    },
    {
      "name": "STATUS_IO_LESEN_GESCHW",
      "status": "ok",
      "instructions": 729,
      "errors": []
    },
    {
      "name": "STATUS_IO_LESEN_ANALOG",
      "status": "ok",
      "instructions": 198,
      "errors": []
    },
    {
      "name": "STATUS_IO_LESEN_DIGITAL",
      "status": "ok",
      "instructions": 1366,
      "errors": []
    },
    {
      "name": "STATUS_4_DRUCKWERTE",
      "status": "ok",
      "instructions": 864,
      "errors": []
    },
    {
      "name": "STATUS_IO_LESEN_CAN",
      "status": "ok",
      "instructions": 374,
      "errors": []
    },
    {
      "name": "DOWNLOAD_STELLGLIED",
      "status": "ok",
      "instructions": 102,
      "errors": []
    },
    {
      "name": "DOWNLOAD_D4_STELLGLIED",
      "status": "ok",
      "instructions": 102,
      "errors": []
    },
    {
      "name": "DOWNLOAD_FUEHLER_EINZELN",
      "status": "ok",
      "instructions": 102,
      "errors": []
    },
    {
      "name": "DOWNLOAD_STATISCH",
      "status": "ok",
      "instructions": 102,
      "errors": []
    },
    {
      "name": "DOWNLOAD_FUEHLER_ALLE",
      "status": "ok",
      "instructions": 102,
      "errors": []
    },
    {
      "name": "DOWNLOAD_EEPROM",
      "status": "ok",
      "instructions": 102,
      "errors": []
    },
    {
      "name": "DOWNLOAD_FS_RESET",
      "status": "ok",
      "instructions": 102,
      "errors": []
    },
    {
      "name": "TEST_D_STELLGLIED",
      "status": "ok",
      "instructions": 886,
      "errors": []
    },
    {
      "name": "TEST_D4_STELLGLIED",
      "status": "ok",
      "instructions": 1430,
      "errors": []
    },
    {
      "name": "TEST_ZUENDWINKEL",
      "status": "ok",
      "instructions": 996,
      "errors": []
    },
    {
      "name": "TEST_FUEHLER_EINZELN",
      "status": "ok",
      "instructions": 327,
      "errors": []
    },
    {
      "name": "TEST_FUEHLER_IMPULS",
      "status": "ok",
      "instructions": 327,
      "errors": []
    },
    {
      "name": "TEST_STATISCH",
      "status": "ok",
      "instructions": 158,
      "errors": []
    },
    {
      "name": "TEST_FUEHLER_ALLE",
      "status": "ok",
      "instructions": 253,
      "errors": []
    },
    {
      "name": "TEST_LENKWINKEL",
      "status": "ok",
      "instructions": 80,
      "errors": []
    },
    {
      "name": "TEST_QUERBESCHLEUNIGUNG",
      "status": "ok",
      "instructions": 524,
      "errors": []
    },
    {
      "name": "TEST_DRUCK",
      "status": "ok",
      "instructions": 313,
      "errors": []
    },
    {
      "name": "TEST_EEPROM_LESEN",
      "status": "ok",
      "instructions": 388,
      "errors": []
    },
    {
      "name": "TEST_EEPROM_SCHREIBEN",
      "status": "ok",
      "instructions": 304,
      "errors": []
    },
    {
      "name": "TEST_FS_SCHREIBEN",
      "status": "ok",
      "instructions": 246,
      "errors": []
    },
    {
      "name": "VAKUUM_PUMPE",
      "status": "ok",
      "instructions": 359,
      "errors": []
    },
    {
      "name": "VAKUUM",
      "status": "ok",
      "instructions": 297,
      "errors": []
    },
    {
      "name": "DIAGNOSE_WEITER",
      "status": "ok",
      "instructions": 102,
      "errors": []
    },
    {
      "name": "TEST_DROSSELKLAPPE",
      "status": "ok",
      "instructions": 344,
      "errors": []
    },
    {
      "name": "DOWNLOAD_AKTUATORIK",
      "status": "ok",
      "instructions": 102,
      "errors": []
    },
    {
      "name": "BANDENDE_TEST_PASSIV",
      "status": "ok",
      "instructions": 198,
      "errors": []
    },
    {
      "name": "BANDENDE_TEST_AKTIV",
      "status": "ok",
      "instructions": 198,
      "errors": []
    },
    {
      "name": "TEST_AKTUATORIK",
      "status": "ok",
      "instructions": 268,
      "errors": []
    },
    {
      "name": "FS_LESEN_EEPROM",
      "status": "ok",
      "instructions": 347,
      "errors": []
    },
    {
      "name": "PRUEFSTEMPEL_SCHREIBEN",
      "status": "ok",
      "instructions": 42,
      "errors": []
    },
    {
      "name": "PRUEFSTEMPEL_LESEN",
      "status": "ok",
      "instructions": 191,
      "errors": []
    },
    {
      "name": "DIAGNOSE_ENDE",
      "status": "ok",
      "instructions": 102,
      "errors": []
    }
  ]
}