{
  "file": "C_DSC57.prg",
  "status": "ok",
  "jobs": [
    {
      "name": "INFO",
      "status": "ok",
      "instructions": 31,
      "errors": []
    },
    {
      "name": "INITIALISIERUNG",
      "status": "ok",
      "instructions": 42,
      "errors": []
    },
    {
      "name": "IDENT",
      "status": "ok",
      "instructions": 102,
      "errors": []
    },
    {
      "name": "C_C_AUFTRAG",
      "status": "ok",
      "instructions": 456,
      "errors": []
    },
    {
      "name": "C_C_LESEN",
      "status": "ok",
      "instructions": 25,
      "errors": []
    },
    {
      "name": "C_FG_AUFTRAG",
      "status": "ok",
      "instructions": 200,
      "errors": []
    },
    {
      "name": "C_FG_LESEN",
      "status": "ok",
      "instructions": 167,
      "errors": []
    },
    {
      "name": "DIAGNOSE_ENDE",
      "status": "ok",
      "instructions": 74,
      "errors": []
    }
  ]
}